[
    {
        "ProfileID": 4,
        "ProfileName": "JBJKBIK",
        "ModelID": 1,
        "ModelName": "Model (GPNP3 & GPRATIO)",
        "ODSQuery": "",
        "FileType": "C",
        "UserID": 1,
        "AssessmentYear": 2013,
        "JobId": 4,
        "BranchCode": 29,
        "Saved": false,
        "ProfileParametersJson": "",
        "StateCode": null,
        "BusinessCode": null,
        "JobStatus": "Done",
        "User": null,
        "Model": null
    },
    {
        "ProfileID": 5,
        "ProfileName": "XDHXZDHGZSD",
        "ModelID": 2,
        "ModelName": "Model (OV_DIR)",
        "ODSQuery": "",
        "FileType": "C",
        "UserID": 1,
        "AssessmentYear": 2012,
        "JobId": 5,
        "BranchCode": 9,
        "Saved": true,
        "ProfileParametersJson": "",
        "StateCode": null,
        "BusinessCode": null,
        "JobStatus": "Done",
        "User": null,
        "Model": null
    },
    {
        "ProfileID": 6,
        "ProfileName": "EGRG",
        "ModelID": 3,
        "ModelName": "Model (GPNP & EXPTAX)",
        "ODSQuery": "",
        "FileType": "OG",
        "UserID": 1,
        "AssessmentYear": 2013,
        "JobId": 6,
        "BranchCode": 9,
        "Saved": false,
        "ProfileParametersJson": "",
        "StateCode": null,
        "BusinessCode": null,
        "JobStatus": "Done",
        "User": null,
        "Model": null
    },
    {
        "ProfileID": 7,
        "ProfileName": "fsee",
        "ModelID": 2,
        "ModelName": "Model (OV_DIR)",
        "ODSQuery": "",
        "FileType": "OG",
        "UserID": 1,
        "AssessmentYear": 2013,
        "JobId": 7,
        "BranchCode": 32,
        "Saved": false,
        "ProfileParametersJson": "",
        "StateCode": null,
        "BusinessCode": null,
        "JobStatus": "In Queue",
        "User": null,
        "Model": null
    }
]